textstatslite/__init__.py
textstatslite/__main__.py
textstatslite/core.py
textstatslite-0.2.1.dist-info/licenses/License
textstatslite-0.2.1.dist-info/METADATA
textstatslite-0.2.1.dist-info/WHEEL
textstatslite-0.2.1.dist-info/entry_points.txt
textstatslite-0.2.1.dist-info/top_level.txt
textstatslite-0.2.1.dist-info/RECORD
