Metadata-Version: 2.4
Name: textstatslite
Version: 0.2.1
Summary: Lightweight text statistics tool with CLI and readability scoring
Author: Khangesh Matte
Requires-Python: >=3.6
License-File: License
Dynamic: author
Dynamic: description
Dynamic: description-content-type
Dynamic: license-file
Dynamic: requires-python
Dynamic: summary
